<?xml version="1.0" encoding="UTF-8"?>

<!--
FoxClocks extension for Mozilla Firefox/Thunderbird/Sunbird
Copyright (C) 2005-2008 Andy McDonald / www.stemhaus.com
For licensing terms, please refer to readme.txt in this extension's '.xpi'
package or its installation directory on your computer.
-->

<!-- Please see 'NOTES FOR TRANSLATORS' in readme.txt -->

<zonepicker xmlns="http://www.stemhaus.com/firefox/foxclocks/zonepicker" version="2.0" locale="en-GB">
	<Branch name="África">
		<Branch name="Países">
			<Leaf zone_id="Africa/Johannesburg" name="África do Sul" />
			<Leaf zone_id="Africa/Algiers" name="Algéria" />
			<Leaf zone_id="Africa/Luanda" name="Angola" />
			<Leaf zone_id="Africa/Porto-Novo" name="Benin" />
			<Leaf zone_id="Africa/Gaborone" name="Botsuana" />
			<Leaf zone_id="Africa/Ouagadougou" name="Burkina Faso" />
			<Leaf zone_id="Africa/Bujumbura" name="Burundi" />
			<Leaf zone_id="Africa/Douala" name="Camarões" />
			<Leaf zone_id="Africa/Bangui" name="Rep. Centro-Africana" />
			<Leaf zone_id="Africa/Ceuta" name="Ceuta &amp; Melilla" />
			<Leaf zone_id="Africa/Ndjamena" name="Chade" />
			<Branch name="Congo, Rep. Democrática do">
				<Leaf zone_id="Africa/Lubumbashi" name="Congo Oriental" />
				<Leaf zone_id="Africa/Kinshasa" name="Congo Ocidental" />
			</Branch>
			<Leaf zone_id="Africa/Brazzaville" name="Congo, Rep. do" />
			<Leaf zone_id="Africa/Abidjan" name="Costa do Marfim" />
			<Leaf zone_id="Africa/Djibouti" name="Djibouti" />
			<Leaf zone_id="Africa/Cairo" name="Egito" />
			<Leaf zone_id="Africa/Malabo" name="Guiné Equatorial" />
			<Leaf zone_id="Africa/Asmara" name="Eritréia" />
			<Leaf zone_id="Africa/Addis_Ababa" name="Etiópia" />
			<Leaf zone_id="Africa/Libreville" name="Gabão" />
			<Leaf zone_id="Africa/Banjul" name="Gâmbia" />
			<Leaf zone_id="Africa/Accra" name="Gana" />
			<Leaf zone_id="Africa/Conakry" name="Guiné" />
			<Leaf zone_id="Africa/Bissau" name="Guiné-Bissau" />
			<Leaf zone_id="Africa/Nairobi" name="Quênia" />
			<Leaf zone_id="Africa/Maseru" name="Lesoto" />
			<Leaf zone_id="Africa/Monrovia" name="Libéria" />
			<Leaf zone_id="Africa/Tripoli" name="Líbia" />
			<Leaf zone_id="Indian/Antananarivo" name="Madagascar" />
			<Leaf zone_id="Africa/Blantyre" name="Malawi" />
			<Leaf zone_id="Africa/Bamako" name="Mali" />
			<Leaf zone_id="Africa/Nouakchott" name="Mauritânia" />
			<Leaf zone_id="Africa/Casablanca" name="Marrocos" />
			<Leaf zone_id="Africa/Maputo" name="Moçambique" />
			<Leaf zone_id="Africa/Windhoek" name="Namíbia" />
			<Leaf zone_id="Africa/Niamey" name="Níger" />
			<Leaf zone_id="Africa/Lagos" name="Nigéria" />
			<Leaf zone_id="Africa/Kigali" name="Ruanda" />
			<Leaf zone_id="Africa/Sao_Tome" name="São Tomé &amp; Príncipe" />
			<Leaf zone_id="Africa/Dakar" name="Senegal" />
			<Leaf zone_id="Africa/Freetown" name="Serra Leoa" />
			<Leaf zone_id="Africa/Mogadishu" name="Somália" />
			<Leaf zone_id="Africa/Khartoum" name="Sudão" />
			<Leaf zone_id="Africa/Mbabane" name="Suazilândia" />
			<Leaf zone_id="Africa/Dar_es_Salaam" name="Tanzânia" />
			<Leaf zone_id="Africa/Lome" name="Togo" />
			<Leaf zone_id="Africa/Tunis" name="Tunísia" />
			<Leaf zone_id="Africa/Kampala" name="Uganda" />
			<Leaf zone_id="Africa/El_Aaiun" name="Saara Ocidental" />
			<Leaf zone_id="Africa/Lusaka" name="Zâmbia" />
			<Leaf zone_id="Africa/Harare" name="Zimbábue" />
		</Branch>
		<Branch name="Cidades">
			<Leaf zone_id="Africa/Abidjan" name="Abidjan" />
			<Leaf zone_id="Africa/Accra" name="Accra" />
			<Leaf zone_id="Africa/Addis_Ababa" name="Addis Ababa" />
			<Leaf zone_id="Africa/Algiers" name="Algiers" />
			<Leaf zone_id="Indian/Antananarivo" name="Antananarivo" />
			<Leaf zone_id="Africa/Asmara" name="Asmara" />
			<Leaf zone_id="Africa/Bamako" name="Bamako" />
			<Leaf zone_id="Africa/Bangui" name="Bangui" />
			<Leaf zone_id="Africa/Banjul" name="Banjul" />
			<Leaf zone_id="Africa/Bissau" name="Bissau" />
			<Leaf zone_id="Africa/Blantyre" name="Blantyre" />
			<Leaf zone_id="Africa/Brazzaville" name="Brazzaville" />
			<Leaf zone_id="Africa/Bujumbura" name="Bujumbura" />
			<Leaf zone_id="Africa/Cairo" name="Cairo" />
			<Leaf zone_id="Africa/Johannesburg" name="Cape Town">
				<Coordinates latitude="-33.925" longitude="18.43" />
			</Leaf>
			<Leaf zone_id="Africa/Casablanca" name="Casablanca" />
			<Leaf zone_id="Africa/Ceuta" name="Ceuta" />
			<Leaf zone_id="Africa/Conakry" name="Conakry" />
			<Leaf zone_id="Africa/Dakar" name="Dakar" />
			<Leaf zone_id="Africa/Dar_es_Salaam" name="Dar es Salaam" />
			<Leaf zone_id="Africa/Djibouti" name="Djibouti City" />
			<Leaf zone_id="Africa/Douala" name="Douala" />
			<Leaf zone_id="Africa/El_Aaiun" name="El Aaiún" />
			<Leaf zone_id="Africa/Freetown" name="Freetown" />
			<Leaf zone_id="Africa/Gaborone" name="Gaborone" />
			<Leaf zone_id="Africa/Harare" name="Harare" />
			<Leaf zone_id="Africa/Johannesburg" name="Johannesburg" />
			<Leaf zone_id="Africa/Kampala" name="Kampala" />
			<Leaf zone_id="Africa/Khartoum" name="Khartoum" />
			<Leaf zone_id="Africa/Kigali" name="Kigali" />
			<Leaf zone_id="Africa/Kinshasa" name="Kinshasa" />
			<Leaf zone_id="Africa/Lagos" name="Lagos" />
			<Leaf zone_id="Africa/Libreville" name="Libreville" />
			<Leaf zone_id="Africa/Lome" name="Lomé" />
			<Leaf zone_id="Africa/Luanda" name="Luanda" />
			<Leaf zone_id="Africa/Lubumbashi" name="Lubumbashi" />
			<Leaf zone_id="Africa/Lusaka" name="Lusaka" />
			<Leaf zone_id="Africa/Malabo" name="Malabo" />
			<Leaf zone_id="Africa/Maputo" name="Maputo" />
			<Leaf zone_id="Africa/Maseru" name="Maseru" />
			<Leaf zone_id="Africa/Mbabane" name="Mbabane" />
			<Leaf zone_id="Africa/Mogadishu" name="Mogadishu" />
			<Leaf zone_id="Africa/Monrovia" name="Monrovia" />
			<Leaf zone_id="Africa/Nairobi" name="Nairobi" />
			<Leaf zone_id="Africa/Ndjamena" name="N'Djamena" />
			<Leaf zone_id="Africa/Niamey" name="Niamey" />
			<Leaf zone_id="Africa/Nouakchott" name="Nouakchott" />
			<Leaf zone_id="Africa/Ouagadougou" name="Ouagadougou" />
			<Leaf zone_id="Africa/Porto-Novo" name="Porto-Novo" />
			<Leaf zone_id="Africa/Sao_Tome" name="São Tomé" />
			<Leaf zone_id="Africa/Tripoli" name="Tripoli" />
			<Leaf zone_id="Africa/Tunis" name="Tunis" />
			<Leaf zone_id="Africa/Windhoek" name="Windhoek" />
		</Branch>
	</Branch>
	<Branch name="Américas">
		<Branch name="Países">
			<Leaf zone_id="America/Anguilla" name="Anguilla" />
			<Leaf zone_id="America/Antigua" name="Antígua e Barbuda" />
			<Branch name="Argentina">
				<Leaf zone_id="America/Argentina/Cordoba" name="Argentina (maior parte)" />
				<Leaf zone_id="America/Argentina/Buenos_Aires" name="Buenos Aires (BA, CF)" />
				<Leaf zone_id="America/Argentina/Catamarca" name="Catamarca (CT), Chubut (CH)" />
				<Leaf zone_id="America/Argentina/Jujuy" name="Jujuy (JY)" />
				<Leaf zone_id="America/Argentina/La_Rioja" name="La Rioja (LR)" />
				<Leaf zone_id="America/Argentina/Mendoza" name="Mendoza (MZ)" />
				<Leaf zone_id="America/Argentina/San_Juan" name="San Juan (SJ)" />
				<Leaf zone_id="America/Argentina/Rio_Gallegos" name="Santa Cruz (SC)" />
				<Leaf zone_id="America/Argentina/Ushuaia" name="Tierra del Fuego (TF)" />
				<Leaf zone_id="America/Argentina/Tucuman" name="Tucumán (TM)" />
			</Branch>
			<Leaf zone_id="America/Aruba" name="Aruba" />
			<Leaf zone_id="America/Nassau" name="Bahamas" />
			<Leaf zone_id="America/Barbados" name="Barbados" />
			<Leaf zone_id="America/Belize" name="Belize" />
			<Leaf zone_id="America/La_Paz" name="Bolívia" />
			<Branch name="Brasil">
				<Leaf zone_id="America/Rio_Branco" name="Acre" />
				<Leaf zone_id="America/Maceio" name="Alagoas, Sergipe" />
				<Leaf zone_id="America/Belem" name="Amapá, Leste Pará" />
				<Leaf zone_id="America/Noronha" name="Fernando de Noronha" />
				<Leaf zone_id="America/Bahia" name="Bahia" />
				<Leaf zone_id="America/Manaus" name="Leste Amazonas" />
				<Leaf zone_id="America/Cuiaba" name="Mato Grosso" />
				<Leaf zone_id="America/Campo_Grande" name="Mato Grosso do Sul" />
				<Leaf zone_id="America/Fortaleza" name="Nordeste Brasileiro" />
				<Leaf zone_id="America/Recife" name="Pernambuco" />
				<Leaf zone_id="America/Boa_Vista" name="Roraima" />
				<Leaf zone_id="America/Sao_Paulo" name="Sul &amp; Sudeste Brasileiro" />
				<Leaf zone_id="America/Araguaina" name="Tocantins" />
				<Leaf zone_id="America/Eirunepe" name="Oeste Amazonas" />
				<Leaf zone_id="America/Porto_Velho" name="Oeste Para, Rondonia" />
			</Branch>
			<Branch name="Canadá">
				<Branch name="Fuso do atlântico">
					<Leaf zone_id="America/Goose_Bay" name="Labrador" />
					<Leaf zone_id="America/Moncton" name="New Brunswick" />
					<Leaf zone_id="America/Halifax" name="NS &amp; PEI" />
				</Branch>
				<Branch name="Central Standard Time">
					<Leaf zone_id="America/Regina" name="Saskatchewan" />
				</Branch>
				<Branch name="Central Time">
					<Leaf zone_id="America/Winnipeg" name="Manitoba &amp; W ON" />
					<Leaf zone_id="America/Rankin_Inlet" name="Central Nunavut" />
				</Branch>
				<Branch name="Eastern Time">
					<Leaf zone_id="America/Toronto" name="Ontario" />
					<Leaf zone_id="America/Montreal" name="Quebec" />
					<Leaf zone_id="America/Iqaluit" name="E Nunavut" />
				</Branch>
				<Branch name="Mountain Time">
					<Leaf zone_id="America/Edmonton" name="Alberta, E BC &amp; W SK" />
					<Leaf zone_id="America/Yellowknife" name="Central NWT" />
					<Leaf zone_id="America/Cambridge_Bay" name="W Nunavut" />
					<Leaf zone_id="America/Inuvik" name="West NWT" />
				</Branch>
				<Branch name="Newfoundland Time">
					<Leaf zone_id="America/St_Johns" name="NF &amp; SE Labrador" />
				</Branch>
				<Branch name="Pacific Time">
					<Leaf zone_id="America/Dawson" name="N Yukon" />
					<Leaf zone_id="America/Whitehorse" name="S Yukon" />
					<Leaf zone_id="America/Vancouver" name="W British Columbia" />
				</Branch>
				<Branch name="Exceções">
					<Branch name="Atlantic Standard Time">
						<Leaf zone_id="America/Blanc-Sablon" name="QC - Lower N Shore" />
					</Branch>
					<Branch name="Atlantic Time">
						<Leaf zone_id="America/Glace_Bay" name="NS - no DST 1966-1971" />
					</Branch>
					<Branch name="Central Standard Time">
						<Leaf zone_id="America/Swift_Current" name="Saskatchewan - midwest" />
					</Branch>
					<Branch name="Central Time">
						<Leaf zone_id="America/Rainy_River" name="Rainy River &amp; Fort Frances, ON" />
					</Branch>
					<Branch name="Eastern Standard Time">
						<Leaf zone_id="America/Atikokan" name="Atikokan, ON &amp; Southampton I, NU" />
					</Branch>
					<Branch name="Eastern Time">
						<Leaf zone_id="America/Nipigon" name="ON &amp; QC - no DST 1967-1973" />
						<Leaf zone_id="America/Pangnirtung" name="Pangnirtung, NU" />
						<Leaf zone_id="America/Thunder_Bay" name="Thunder Bay, ON" />
					</Branch>
					<Branch name="Mountain Standard Time">
						<Leaf zone_id="America/Dawson_Creek" name="Dawson Cr &amp; Fort St John, BC" />
					</Branch>
				</Branch>
			</Branch>
			<Leaf zone_id="America/Cayman" name="Ilhas Cayman" />
			<Leaf zone_id="America/Santiago" name="Chile" />
			<Leaf zone_id="America/Bogota" name="Colômbia" />
			<Leaf zone_id="America/Costa_Rica" name="Costa Rica" />
			<Leaf zone_id="America/Havana" name="Cuba" />
			<Leaf zone_id="America/Dominica" name="Dominica" />
			<Leaf zone_id="America/Santo_Domingo" name="Rep. Dominicana" />
			<Leaf zone_id="America/Guayaquil" name="Equador">
				<Coordinates latitude="-0.223" longitude="-78.513" />
			</Leaf>
			<Leaf zone_id="America/El_Salvador" name="El Salvador" />
			<Leaf zone_id="America/Cayenne" name="Guiana Francesa" />
			<Branch name="Greenland">
				<Leaf zone_id="America/Godthab" name="Groenlândia (maior parte)" />
				<Leaf zone_id="America/Scoresbysund" name="Scoresbysund/Ittoqqortoormiit" />
				<Leaf zone_id="America/Thule" name="Thule/Pituffik" />
				<Leaf zone_id="America/Danmarkshavn" name="E coast, N of Scoresbysund" />
			</Branch>
			<Leaf zone_id="America/Grenada" name="Granada" />
			<Leaf zone_id="America/Guadeloupe" name="Guadalupe" />
			<Leaf zone_id="America/Guatemala" name="Guatemala" />
			<Leaf zone_id="America/Guyana" name="Guiana" />
			<Leaf zone_id="America/Port-au-Prince" name="Haiti" />
			<Leaf zone_id="America/Tegucigalpa" name="Honduras" />
			<Leaf zone_id="America/Jamaica" name="Jamaica" />
			<Leaf zone_id="America/Martinique" name="Martinica" />
			<Branch name="México">
				<Branch name="Central Time">
					<Leaf zone_id="America/Mexico_City" name="Mex. Central (maior parte)" />
					<Leaf zone_id="America/Merida" name="Campeche, Yucatán" />
					<Leaf zone_id="America/Monterrey" name="Coahuila, Durango, Nuevo Leon, Tamaulipas" />
					<Leaf zone_id="America/Cancun" name="Quintana Roo" />
				</Branch>
				<Branch name="Mountain Standard Time">
					<Leaf zone_id="America/Hermosillo" name="Sonora" />
				</Branch>
				<Branch name="Mountain Time">
					<Leaf zone_id="America/Chihuahua" name="Chihuahua" />
					<Leaf zone_id="America/Mazatlan" name="S Baja, Nayarit, Sinaloa" />
				</Branch>
				<Leaf zone_id="America/Tijuana" name="Mex. Pacific" />
			</Branch>
			<Leaf zone_id="America/Montserrat" name="Montserrat" />
			<Leaf zone_id="America/Curacao" name="Antilhas Holandesas" />
			<Leaf zone_id="America/Managua" name="Nicarágua" />
			<Leaf zone_id="America/Panama" name="Panamá" />
			<Leaf zone_id="America/Asuncion" name="Paraguai" />
			<Leaf zone_id="America/Lima" name="Perú" />
			<Leaf zone_id="America/Puerto_Rico" name="Porto Rico" />
			<Leaf zone_id="America/St_Kitts" name="São Cristóvão e Nevis" />
			<Leaf zone_id="America/St_Lucia" name="Santa Lúcia" />
			<Leaf zone_id="America/Miquelon" name="São Pedro e Miquelão" />
			<Leaf zone_id="America/St_Vincent" name="São Vicente e Granadinas" />
			<Leaf zone_id="America/Paramaribo" name="Suriname" />
			<Leaf zone_id="America/Port_of_Spain" name="Trinidad e Tobago" />
			<Leaf zone_id="America/Grand_Turk" name="Ilhas Turks e Caicos" />
			<Branch name="Estados Unidos">
				<Branch name="Alaska">
					<Leaf zone_id="America/Anchorage" name="Alaska (maior parte)" />
					<Leaf zone_id="America/Juneau" name="Alaska panhandle" />
					<Leaf zone_id="America/Yakutat" name="Alaska panhandle neck" />
					<Leaf zone_id="America/Adak" name="Aleutian Is" />
					<Leaf zone_id="America/Nome" name="W Alaska" />
				</Branch>
				<Leaf zone_id="America/Chicago" name="US Central" />
				<Leaf zone_id="America/New_York" name="US Eastern" />
				<Leaf zone_id="Pacific/Honolulu" name="Hawaii" />
				<Leaf zone_id="America/Denver" name="US Mountain" />
				<Leaf zone_id="America/Los_Angeles" name="US Pacific" />
				<Branch name="Exceptions">
					<Branch name="Central Time">
						<Branch name="Indiana">
							<Leaf zone_id="America/Indiana/Tell_City" name="Perry Co" />
							<Leaf zone_id="America/Indiana/Knox" name="Starke Co" />
						</Branch>
						<Branch name="Michigan">
							<Leaf zone_id="America/Menominee" name="Dickinson, Gogebic, Iron &amp; Menominee Cos" />
						</Branch>
						<Branch name="North Dakota">
							<Leaf zone_id="America/North_Dakota/New_Salem" name="Morton Co (except Mandan area)" />
							<Leaf zone_id="America/North_Dakota/Center" name="Oliver Co" />
						</Branch>
					</Branch>
					<Branch name="Eastern Time">
						<Branch name="Indiana">
							<Leaf zone_id="America/Indiana/Marengo" name="Crawford Co" />
							<Leaf zone_id="America/Indiana/Vincennes" name="Daviess, Dubois, Knox &amp; Martin Cos" />
							<Leaf zone_id="America/Indiana/Indianapolis" name="Indiana (most)" />
							<Leaf zone_id="America/Indiana/Petersburg" name="Pike Co" />
							<Leaf zone_id="America/Indiana/Winamac" name="Pulaski Co" />
							<Leaf zone_id="America/Indiana/Vevay" name="Switzerland Co" />
						</Branch>
						<Branch name="Kentucky">
							<Leaf zone_id="America/Kentucky/Louisville" name="Louisville area" />
							<Leaf zone_id="America/Kentucky/Monticello" name="Wayne Co" />
						</Branch>
						<Leaf zone_id="America/Detroit" name="Michigan (most)" />
					</Branch>
					<Branch name="Mountain Time">
						<Leaf zone_id="America/Phoenix" name="Arizona" />
						<Leaf zone_id="America/Shiprock" name="Navajo" />
						<Leaf zone_id="America/Boise" name="S Idaho &amp; E Oregon" />
					</Branch>
				</Branch>
			</Branch>
			<Leaf zone_id="America/Montevideo" name="Uruguai" />
			<Leaf zone_id="America/Caracas" name="Venezuela" />
			<Leaf zone_id="America/Tortola" name="Ilhas Virgens Britânicas" />
			<Leaf zone_id="America/St_Thomas" name="Ilhas Virgens EUA" />
		</Branch>
		<Branch name="Cidades">
			<Leaf zone_id="America/Adak" name="Adak" />
			<Leaf zone_id="America/Anchorage" name="Anchorage" />
			<Leaf zone_id="America/Araguaina" name="Araguaina" />
			<Leaf zone_id="America/Asuncion" name="Asunción" />
			<Leaf zone_id="America/Atikokan" name="Atikokan" />
			<Leaf zone_id="America/Bahia" name="Bahia" />
			<Leaf zone_id="America/Guadeloupe" name="Basse-Terre, Guadeloupe" />
			<Leaf zone_id="America/St_Kitts" name="Basseterre, St Kitts" />
			<Leaf zone_id="America/Belem" name="Belém" />
			<Leaf zone_id="America/Belize" name="Belize City" />
			<Leaf zone_id="America/Blanc-Sablon" name="Blanc-Sablon" />
			<Leaf zone_id="America/Boa_Vista" name="Boa Vista" />
			<Leaf zone_id="America/Bogota" name="Bogotá" />
			<Leaf zone_id="America/Boise" name="Boise" />
			<Leaf zone_id="America/Sao_Paulo" name="Brasília">
				<Coordinates latitude="-15.792" longitude="-47.898" />
			</Leaf>
			<Leaf zone_id="America/Barbados" name="Bridgetown" />
			<Leaf zone_id="America/Argentina/Buenos_Aires" name="Buenos Aires" />
			<Leaf zone_id="America/Cambridge_Bay" name="Cambridge Bay" />
			<Leaf zone_id="America/Campo_Grande" name="Campo Grande" />
			<Leaf zone_id="America/Cancun" name="Cancún" />
			<Leaf zone_id="America/Caracas" name="Caracas" />
			<Leaf zone_id="America/Argentina/Catamarca" name="Catamarca" />
			<Leaf zone_id="America/Cayenne" name="Cayenne" />
			<Leaf zone_id="America/Chicago" name="Chicago" />
			<Leaf zone_id="America/Chihuahua" name="Chihuahua" />
			<Leaf zone_id="America/Grand_Turk" name="Cockburn Town" />
			<Leaf zone_id="America/Argentina/Cordoba" name="Córdoba" />
			<Leaf zone_id="America/Cuiaba" name="Cuiabá" />
			<Leaf zone_id="America/Danmarkshavn" name="Danmarkshavn" />
			<Leaf zone_id="America/Dawson" name="Dawson City" />
			<Leaf zone_id="America/Dawson_Creek" name="Dawson Creek" />
			<Leaf zone_id="America/Denver" name="Denver" />
			<Leaf zone_id="America/Detroit" name="Detroit" />
			<Leaf zone_id="America/Edmonton" name="Edmonton" />
			<Leaf zone_id="America/Eirunepe" name="Eirunepe" />
			<Leaf zone_id="America/Martinique" name="Fort-de-France" />
			<Leaf zone_id="America/Fortaleza" name="Fortaleza" />
			<Leaf zone_id="America/Cayman" name="George Town, Cayman Is" />
			<Leaf zone_id="America/Guyana" name="Georgetown, Guyana" />
			<Leaf zone_id="America/Glace_Bay" name="Glace Bay" />
			<Leaf zone_id="America/Godthab" name="Godthab" />
			<Leaf zone_id="America/Goose_Bay" name="Goose Bay" />
			<Leaf zone_id="America/Guatemala" name="Guatemala City" />
			<Leaf zone_id="America/Guayaquil" name="Guayaquil" />
			<Leaf zone_id="America/Halifax" name="Halifax" />
			<Leaf zone_id="America/Havana" name="Havana" />
			<Leaf zone_id="America/Hermosillo" name="Hermosillo" />
			<Leaf zone_id="Pacific/Honolulu" name="Honolulu" />
			<Branch name="Indiana">
				<Leaf zone_id="America/Indiana/Indianapolis" name="Indianápolis" />
				<Leaf zone_id="America/Indiana/Knox" name="Knox" />
				<Leaf zone_id="America/Indiana/Marengo" name="Marengo" />
				<Leaf zone_id="America/Indiana/Petersburg" name="Petersburg" />
				<Leaf zone_id="America/Indiana/Tell_City" name="Tell City" />
				<Leaf zone_id="America/Indiana/Vevay" name="Vevay" />
				<Leaf zone_id="America/Indiana/Vincennes" name="Vincennes" />
				<Leaf zone_id="America/Indiana/Winamac" name="Winamac" />
			</Branch>
			<Leaf zone_id="America/Inuvik" name="Inuvik" />
			<Leaf zone_id="America/Iqaluit" name="Iqaluit" />
			<Leaf zone_id="America/Argentina/Jujuy" name="Jujuy" />
			<Leaf zone_id="America/Juneau" name="Juneau" />
			<Branch name="Kentucky">
				<Leaf zone_id="America/Kentucky/Louisville" name="Louisville" />
				<Leaf zone_id="America/Kentucky/Monticello" name="Monticello" />
			</Branch>
			<Leaf zone_id="America/Jamaica" name="Kingston" />
			<Leaf zone_id="America/La_Paz" name="La Paz" />
			<Leaf zone_id="America/Argentina/La_Rioja" name="La Rioja" />
			<Leaf zone_id="America/Lima" name="Lima" />
			<Leaf zone_id="America/Los_Angeles" name="Los Angeles" />
			<Leaf zone_id="America/Maceio" name="Maceió" />
			<Leaf zone_id="America/Managua" name="Managua" />
			<Leaf zone_id="America/Manaus" name="Manaus" />
			<Leaf zone_id="America/Mazatlan" name="Mazatlán" />
			<Leaf zone_id="America/Argentina/Mendoza" name="Mendoza" />
			<Leaf zone_id="America/Menominee" name="Menominee" />
			<Leaf zone_id="America/Merida" name="Mérida" />
			<Leaf zone_id="America/Mexico_City" name="Mexico City" />
			<Leaf zone_id="America/Miquelon" name="Miquelon" />
			<Leaf zone_id="America/Moncton" name="Moncton" />
			<Leaf zone_id="America/Monterrey" name="Monterrey" />
			<Leaf zone_id="America/Montevideo" name="Montevideo" />
			<Leaf zone_id="America/Montreal" name="Montreal" />
			<Leaf zone_id="America/Nassau" name="Nassau" />
			<Leaf zone_id="America/New_York" name="New York" />
			<Leaf zone_id="America/Nipigon" name="Nipigon" />
			<Leaf zone_id="America/Nome" name="Nome" />
			<Leaf zone_id="America/Noronha" name="Noronha" />
			<Branch name="North Dakota">
				<Leaf zone_id="America/North_Dakota/Center" name="Center" />
				<Leaf zone_id="America/North_Dakota/New_Salem" name="New Salem" />
			</Branch>
			<Leaf zone_id="America/Aruba" name="Oranjestad" />
			<Leaf zone_id="America/Panama" name="Panama City" />
			<Leaf zone_id="America/Pangnirtung" name="Pangnirtung" />
			<Leaf zone_id="America/Paramaribo" name="Paramaribo" />
			<Leaf zone_id="America/Phoenix" name="Phoenix" />
			<Leaf zone_id="America/Montserrat" name="Plymouth" />
			<Leaf zone_id="America/Port_of_Spain" name="Port of Spain" />
			<Leaf zone_id="America/Port-au-Prince" name="Port-au-Prince" />
			<Leaf zone_id="America/Porto_Velho" name="Porto Velho" />
			<Leaf zone_id="America/Guayaquil" name="Quito">
				<Coordinates latitude="-0.223" longitude="-78.513" />
			</Leaf>
			<Leaf zone_id="America/Rainy_River" name="Rainy River" />
			<Leaf zone_id="America/Rankin_Inlet" name="Rankin Inlet" />
			<Leaf zone_id="America/Recife" name="Recife" />
			<Leaf zone_id="America/Regina" name="Regina" />
			<Leaf zone_id="America/Rio_Branco" name="Rio Branco" />
			<Leaf zone_id="America/Sao_Paulo" name="Rio de Janeiro">
				<Coordinates latitude="-22.909" longitude="-43.215" />
			</Leaf>
			<Leaf zone_id="America/Argentina/Rio_Gallegos" name="Río Gallegos" />
			<Leaf zone_id="America/Dominica" name="Roseau" />
			<Leaf zone_id="America/Grenada" name="St. George's" />
			<Leaf zone_id="America/Antigua" name="St John's, Antigua" />
			<Leaf zone_id="America/St_Johns" name="St John's, Nfld" />
			<Leaf zone_id="America/St_Lucia" name="St Lucia" />
			<Leaf zone_id="America/St_Thomas" name="St Thomas" />
			<Leaf zone_id="America/St_Vincent" name="St Vincent" />
			<Leaf zone_id="America/Costa_Rica" name="San José" />
			<Leaf zone_id="America/Argentina/San_Juan" name="San Juan, Argentina" />
			<Leaf zone_id="America/Puerto_Rico" name="San Juan, Puerto Rico" />
			<Leaf zone_id="America/El_Salvador" name="San Salvador" />
			<Leaf zone_id="America/Santiago" name="Santiago" />
			<Leaf zone_id="America/Santo_Domingo" name="Santo Domingo" />
			<Leaf zone_id="America/Sao_Paulo" name="São Paulo" />
			<Leaf zone_id="America/Scoresbysund" name="Scoresbysund" />
			<Leaf zone_id="America/Shiprock" name="Shiprock" />
			<Leaf zone_id="America/Swift_Current" name="Swift Current" />
			<Leaf zone_id="America/Tegucigalpa" name="Tegucigalpa" />
			<Leaf zone_id="America/Anguilla" name="The Valley" />
			<Leaf zone_id="America/Thule" name="Thule" />
			<Leaf zone_id="America/Thunder_Bay" name="Thunder Bay" />
			<Leaf zone_id="America/Tijuana" name="Tijuana" />
			<Leaf zone_id="America/Toronto" name="Toronto" />
			<Leaf zone_id="America/Tortola" name="Tortola" />
			<Leaf zone_id="America/Argentina/Tucuman" name="Tucumán" />
			<Leaf zone_id="America/Argentina/Ushuaia" name="Ushuaia" />
			<Leaf zone_id="America/Vancouver" name="Vancouver" />
			<Leaf zone_id="America/New_York" name="Washington, DC">
				<Coordinates latitude="38.895" longitude="-77.037" />
			</Leaf>
			<Leaf zone_id="America/Whitehorse" name="Whitehorse" />
			<Leaf zone_id="America/Curacao" name="Willemstad" />
			<Leaf zone_id="America/Winnipeg" name="Winnipeg" />
			<Leaf zone_id="America/Yakutat" name="Yakutat" />
			<Leaf zone_id="America/Yellowknife" name="Yellowknife" />
		</Branch>
	</Branch>
	<Branch name="Antártida">
		<Leaf zone_id="Antarctica/South_Pole" name="Amundsen-Scott Stn, South Pole" />
		<Leaf zone_id="Antarctica/Casey" name="Casey Stn, Bailey Peninsula" />
		<Leaf zone_id="Antarctica/Davis" name="Davis Stn, Vestfold Hills" />
		<Leaf zone_id="Antarctica/DumontDUrville" name="Dumont d'Urville Stn, Terre Adelie" />
		<Leaf zone_id="Antarctica/McMurdo" name="McMurdo Stn, Ross I" />
		<Leaf zone_id="Antarctica/Mawson" name="Mawson Stn, Holme Bay" />
		<Leaf zone_id="Antarctica/Palmer" name="Palmer Stn, Anvers I" />
		<Leaf zone_id="Antarctica/Rothera" name="Rothera Stn, Adelaide I" />
		<Leaf zone_id="Antarctica/Syowa" name="Syowa Stn, E Ongul I" />
		<Leaf zone_id="Antarctica/Vostok" name="Vostok Stn, S Magnetic Pole" />
	</Branch>
	<Branch name="Oceano Ártico">
		<Branch name="Svalbard &amp; Jan Mayen">
			<Leaf zone_id="Arctic/Longyearbyen" name="Svalbard" />
		</Branch>
	</Branch>
	<Branch name="Ásia">
		<Branch name="Países">
			<Leaf zone_id="Asia/Kabul" name="Afeganistão" />
			<Leaf zone_id="Asia/Yerevan" name="Armênia" />
			<Leaf zone_id="Asia/Baku" name="Azerbaijão" />
			<Leaf zone_id="Asia/Bahrain" name="Barém" />
			<Leaf zone_id="Asia/Dhaka" name="Bangladesh" />
			<Leaf zone_id="Asia/Thimphu" name="Butão" />
			<Leaf zone_id="Asia/Brunei" name="Brunei" />
			<Leaf zone_id="Asia/Phnom_Penh" name="Camboja" />
			<Leaf zone_id="Asia/Shanghai" name="China">
				<Coordinates latitude="39.904" longitude="116.391" />
			</Leaf>
			<Branch name="China (histórica)">
				<Leaf zone_id="Asia/Harbin" name="Heilongjiang (except Mohe), Jilin" />
				<Leaf zone_id="Asia/Chongqing" name="Central China" />
				<Leaf zone_id="Asia/Urumqi" name="Tibet &amp; Xinjiang (most)" />
				<Leaf zone_id="Asia/Kashgar" name="W Tibet &amp; Xinjiang" />
			</Branch>
			<Leaf zone_id="Asia/Nicosia" name="Chipre" />
			<Leaf zone_id="Asia/Dili" name="Timor Leste" />
			<Leaf zone_id="Asia/Tbilisi" name="Geórgia" />
			<Leaf zone_id="Asia/Hong_Kong" name="Hong Kong" />
			<Leaf zone_id="Asia/Calcutta" name="Índia">
				<Coordinates latitude="28.633" longitude="77.217" />
			</Leaf>
			<Branch name="Indonésia">
				<Leaf zone_id="Asia/Jayapura" name="Irian Jaya &amp; Moluccas" />
				<Leaf zone_id="Asia/Jakarta" name="Java &amp; Sumatra" />
				<Leaf zone_id="Asia/Makassar" name="E &amp; S Borneo, Sulawesi, Bali &amp; East" />
				<Leaf zone_id="Asia/Pontianak" name="W &amp; Central Borneo" />
			</Branch>
			<Leaf zone_id="Asia/Tehran" name="Irã" />
			<Leaf zone_id="Asia/Baghdad" name="Iraque" />
			<Leaf zone_id="Asia/Jerusalem" name="Israel" />
			<Leaf zone_id="Asia/Tokyo" name="Japão" />
			<Leaf zone_id="Asia/Amman" name="Jordânia" />
			<Branch name="Cazaquistão">
				<Leaf zone_id="Asia/Almaty" name="Cazaquistão (maior parte)" />
				<Leaf zone_id="Asia/Aqtobe" name="Aqtobe" />
				<Leaf zone_id="Asia/Aqtau" name="Atyrau, Mangghystau" />
				<Leaf zone_id="Asia/Qyzylorda" name="Qyzylorda" />
				<Leaf zone_id="Asia/Oral" name="W Kazakhstan" />
			</Branch>
			<Leaf zone_id="Asia/Pyongyang" name="Coréia do Norte" />
			<Leaf zone_id="Asia/Seoul" name="Coréia do Sul" />
			<Leaf zone_id="Asia/Kuwait" name="Kuwait" />
			<Leaf zone_id="Asia/Bishkek" name="Quirguistão" />
			<Leaf zone_id="Asia/Vientiane" name="Laos" />
			<Leaf zone_id="Asia/Beirut" name="Líbano" />
			<Leaf zone_id="Asia/Macau" name="Macau" />
			<Branch name="Malásia">
				<Leaf zone_id="Asia/Kuala_Lumpur" name="Malásia Peninsular" />
				<Leaf zone_id="Asia/Kuching" name="Sabah &amp; Sarawak" />
			</Branch>
			<Branch name="Mongólia">
				<Leaf zone_id="Asia/Ulaanbaatar" name="Mongólia (maior parte)" />
				<Leaf zone_id="Asia/Hovd" name="Bayan-Olgiy, Hovd, etc." />
				<Leaf zone_id="Asia/Choibalsan" name="Dornod, Sukhbaatar" />
			</Branch>
			<Leaf zone_id="Asia/Rangoon" name="Mianmar (Burma)" />
			<Leaf zone_id="Asia/Kathmandu" name="Nepal" />
			<Leaf zone_id="Asia/Muscat" name="Omã" />
			<Leaf zone_id="Asia/Karachi" name="Paquistão" />
			<Leaf zone_id="Asia/Gaza" name="Palestina" />
			<Leaf zone_id="Asia/Manila" name="Filipinas" />
			<Leaf zone_id="Asia/Qatar" name="Catar" />
			<Branch name="Rússia">
				<Leaf zone_id="Asia/Yekaterinburg" name="Moscou+02 - Urals" />
				<Leaf zone_id="Asia/Novosibirsk" name="Moscou+03 - Novosibirsk" />
				<Leaf zone_id="Asia/Omsk" name="Moscou+03 - W Siberia" />
				<Leaf zone_id="Asia/Krasnoyarsk" name="Moscou+04 - R Yenisei" />
				<Leaf zone_id="Asia/Irkutsk" name="Moscou+05 - L Baikal" />
				<Leaf zone_id="Asia/Yakutsk" name="Moscou+06 - R Lena" />
				<Leaf zone_id="Asia/Vladivostok" name="Moscou+07 - R Amur" />
				<Leaf zone_id="Asia/Sakhalin" name="Moscou+07 - Sakhalin I" />
				<Leaf zone_id="Asia/Magadan" name="Moscou+08 - Magadan" />
				<Leaf zone_id="Asia/Kamchatka" name="Moscou+09 - Kamchatka" />
				<Leaf zone_id="Asia/Anadyr" name="Moscou+10 - Bering Sea" />
			</Branch>
			<Leaf zone_id="Asia/Riyadh" name="Arábia Saudita" />
			<Leaf zone_id="Asia/Singapore" name="Singapura" />
			<Leaf zone_id="Asia/Colombo" name="Sri Lanka" />
			<Leaf zone_id="Asia/Damascus" name="Síria" />
			<Leaf zone_id="Asia/Taipei" name="Taiwan" />
			<Leaf zone_id="Asia/Dushanbe" name="Tajiquistão" />
			<Leaf zone_id="Asia/Bangkok" name="Tailândia" />
			<Leaf zone_id="Asia/Ashgabat" name="Turcomenistão" />
			<Leaf zone_id="Europe/Istanbul" name="Turquia" />
			<Leaf zone_id="Asia/Dubai" name="Emirados Árabes Unidos" />
			<Branch name="Uzbequistão">
				<Leaf zone_id="Asia/Tashkent" name="E Uzbequistão" />
				<Leaf zone_id="Asia/Samarkand" name="W Uzbequistão" />
			</Branch>
			<Leaf zone_id="Asia/Saigon" name="Vietnã" />
			<Leaf zone_id="Asia/Aden" name="Iêmen">
				<Coordinates latitude="15.352" longitude="44.207" />
			</Leaf>
		</Branch>
		<Branch name="Cidades">
			<Leaf zone_id="Asia/Aden" name="Aden" />
			<Leaf zone_id="Asia/Almaty" name="Almaty" />
			<Leaf zone_id="Asia/Amman" name="Amman" />
			<Leaf zone_id="Asia/Anadyr" name="Anadyr" />
			<Leaf zone_id="Asia/Aqtau" name="Aqtau" />
			<Leaf zone_id="Asia/Aqtobe" name="Aqtobe" />
			<Leaf zone_id="Asia/Ashgabat" name="Ashgabat" />
			<Leaf zone_id="Asia/Baghdad" name="Bagdá" />
			<Leaf zone_id="Asia/Baku" name="Baku" />
			<Leaf zone_id="Asia/Brunei" name="Bandar Seri Begawan" />
			<Leaf zone_id="Asia/Bangkok" name="Bangkok" />
			<Leaf zone_id="Asia/Shanghai" name="Beijing">
				<Coordinates latitude="39.904" longitude="116.391" />
			</Leaf>
			<Leaf zone_id="Asia/Beirut" name="Beirute" />
			<Leaf zone_id="Asia/Bishkek" name="Bishkek" />
			<Leaf zone_id="Asia/Choibalsan" name="Choibalsan" />
			<Leaf zone_id="Asia/Chongqing" name="Chongqing" />
			<Leaf zone_id="Asia/Colombo" name="Colombo" />
			<Leaf zone_id="Asia/Damascus" name="Damascus" />
			<Leaf zone_id="Asia/Dhaka" name="Dhaka" />
			<Leaf zone_id="Asia/Dili" name="Dili" />
			<Leaf zone_id="Asia/Qatar" name="Doha" />
			<Leaf zone_id="Asia/Dubai" name="Dubai" />
			<Leaf zone_id="Asia/Dushanbe" name="Dushanbe" />
			<Leaf zone_id="Asia/Gaza" name="Gaza" />
			<Leaf zone_id="Asia/Harbin" name="Harbin" />
			<Leaf zone_id="Asia/Hong_Kong" name="Hong Kong" />
			<Leaf zone_id="Asia/Hovd" name="Hovd" />
			<Leaf zone_id="Asia/Irkutsk" name="Irkutsk" />
			<Leaf zone_id="Asia/Karachi" name="Islamabad">
				<Coordinates latitude="33.718" longitude="73.061" />
			</Leaf>
			<Leaf zone_id="Europe/Istanbul" name="Istanbul" />
			<Leaf zone_id="Asia/Jakarta" name="Jakarta" />
			<Leaf zone_id="Asia/Jayapura" name="Jayapura" />
			<Leaf zone_id="Asia/Jerusalem" name="Jerusalem" />
			<Leaf zone_id="Asia/Kabul" name="Kabul" />
			<Leaf zone_id="Asia/Karachi" name="Karachi" />
			<Leaf zone_id="Asia/Kashgar" name="Kashgar" />
			<Leaf zone_id="Asia/Kathmandu" name="Kathmandu" />
			<Leaf zone_id="Asia/Calcutta" name="Kolkata (Calcutta)" />
			<Leaf zone_id="Asia/Krasnoyarsk" name="Krasnoyarsk" />
			<Leaf zone_id="Asia/Kuala_Lumpur" name="Kuala Lumpur" />
			<Leaf zone_id="Asia/Kuching" name="Kuching" />
			<Leaf zone_id="Asia/Kuwait" name="Kuwait City" />
			<Leaf zone_id="Asia/Macau" name="Macau" />
			<Leaf zone_id="Asia/Magadan" name="Magadan" />
			<Leaf zone_id="Asia/Makassar" name="Makassar" />
			<Leaf zone_id="Asia/Bahrain" name="Manama" />
			<Leaf zone_id="Asia/Manila" name="Manila" />
			<Leaf zone_id="Asia/Calcutta" name="Mumbai (Bombay)">
				<Coordinates latitude="19.032" longitude="72.849" />
			</Leaf>
			<Leaf zone_id="Asia/Muscat" name="Muscat" />
			<Leaf zone_id="Asia/Calcutta" name="New Delhi">
				<Coordinates latitude="28.633" longitude="77.217" />
			</Leaf>
			<Leaf zone_id="Asia/Nicosia" name="Nicosia" />
			<Leaf zone_id="Asia/Novosibirsk" name="Novosibirsk" />
			<Leaf zone_id="Asia/Omsk" name="Omsk" />
			<Leaf zone_id="Asia/Oral" name="Oral" />
			<Leaf zone_id="Asia/Kamchatka" name="Petropavlovsk-Kamchatsky" />
			<Leaf zone_id="Asia/Phnom_Penh" name="Phnom Penh" />
			<Leaf zone_id="Asia/Pontianak" name="Pontianak" />
			<Leaf zone_id="Asia/Pyongyang" name="Pyongyang" />
			<Leaf zone_id="Asia/Qyzylorda" name="Qyzylorda" />
			<Leaf zone_id="Asia/Rangoon" name="Rangoon" />
			<Leaf zone_id="Asia/Riyadh" name="Riyadh" />
			<Leaf zone_id="Asia/Saigon" name="Saigon" />
			<Leaf zone_id="Asia/Samarkand" name="Samarkand" />
			<Leaf zone_id="Asia/Aden" name="San‘a’">
				<Coordinates latitude="15.352" longitude="44.207" />
			</Leaf>
			<Leaf zone_id="Asia/Seoul" name="Seoul" />
			<Leaf zone_id="Asia/Shanghai" name="Shanghai" />
			<Leaf zone_id="Asia/Singapore" name="Singapore" />
			<Leaf zone_id="Asia/Taipei" name="Taipei" />
			<Leaf zone_id="Asia/Tashkent" name="Tashkent" />
			<Leaf zone_id="Asia/Tbilisi" name="Tbilisi" />
			<Leaf zone_id="Asia/Tehran" name="Tehran" />
			<Leaf zone_id="Asia/Thimphu" name="Thimphu" />
			<Leaf zone_id="Asia/Tokyo" name="Tokyo" />
			<Leaf zone_id="Asia/Ulaanbaatar" name="Ulaanbaatar" />
			<Leaf zone_id="Asia/Urumqi" name="Ürümqi" />
			<Leaf zone_id="Asia/Vientiane" name="Vientiane" />
			<Leaf zone_id="Asia/Vladivostok" name="Vladivostok" />
			<Leaf zone_id="Asia/Yakutsk" name="Yakutsk" />
			<Leaf zone_id="Asia/Yekaterinburg" name="Yekaterinburg" />
			<Leaf zone_id="Asia/Yerevan" name="Yerevan" />
			<Leaf zone_id="Asia/Sakhalin" name="Yuzhno-Sakhalinsk" />
		</Branch>
	</Branch>
	<Branch name="Oceano Atlântico">
		<Leaf zone_id="Atlantic/Bermuda" name="Bermuda" />
		<Leaf zone_id="Atlantic/Cape_Verde" name="Cape Verde" />
		<Leaf zone_id="Atlantic/Faroe" name="Faroe Is" />
		<Leaf zone_id="Atlantic/Stanley" name="Falkland Is" />
		<Leaf zone_id="Atlantic/Reykjavik" name="Iceland" />
		<Branch name="Portugal">
			<Leaf zone_id="Atlantic/Azores" name="Azores" />
			<Leaf zone_id="Atlantic/Madeira" name="Madeira" />
		</Branch>
		<Leaf zone_id="Atlantic/St_Helena" name="St Helena" />
		<Leaf zone_id="Atlantic/South_Georgia" name="S Georgia &amp; S Sandwich Is" />
		<Branch name="Spain">
			<Leaf zone_id="Atlantic/Canary" name="Canary Is" />
		</Branch>
		<Branch name="Svalbard &amp; Jan Mayen">
			<Leaf zone_id="Europe/Oslo" name="Jan Mayen">
				<Coordinates latitude="70.983" longitude="-8.083" />
			</Leaf>
		</Branch>
	</Branch>
	<Branch name="Austrália">
		<Branch name="Estados">
			<Leaf zone_id="Australia/Lord_Howe" name="Lord Howe I" />
			<Leaf zone_id="Australia/Sydney" name="NSW" />
			<Leaf zone_id="Australia/Broken_Hill" name="NSW - Yancowinna" />
			<Leaf zone_id="Australia/Darwin" name="N Territory" />
			<Leaf zone_id="Australia/Brisbane" name="Queensland" />
			<Leaf zone_id="Australia/Lindeman" name="Queensland - Holiday Is" />
			<Leaf zone_id="Australia/Adelaide" name="S Australia" />
			<Leaf zone_id="Australia/Hobart" name="Tasmania" />
			<Leaf zone_id="Australia/Currie" name="Tasmania - King I" />
			<Leaf zone_id="Australia/Melbourne" name="Victoria" />
			<Leaf zone_id="Australia/Perth" name="W Australia" />
		</Branch>
		<Branch name="Cidades">
			<Leaf zone_id="Australia/Adelaide" name="Adelaide" />
			<Leaf zone_id="Australia/Brisbane" name="Brisbane" />
			<Leaf zone_id="Australia/Broken_Hill" name="Broken Hill" />
			<Leaf zone_id="Australia/Sydney" name="Canberra">
				<Coordinates latitude="-35.308" longitude="149.124" />
			</Leaf>
			<Leaf zone_id="Australia/Currie" name="Currie" />
			<Leaf zone_id="Australia/Darwin" name="Darwin" />
			<Leaf zone_id="Australia/Hobart" name="Hobart" />
			<Leaf zone_id="Australia/Lindeman" name="Lindeman I" />
			<Leaf zone_id="Australia/Lord_Howe" name="Lord Howe I" />
			<Leaf zone_id="Australia/Melbourne" name="Melbourne" />
			<Leaf zone_id="Australia/Perth" name="Perth" />
			<Leaf zone_id="Australia/Sydney" name="Sydney" />
		</Branch>
	</Branch>
	<Branch name="Europa">
		<Branch name="Países">
			<Leaf zone_id="Europe/Tirane" name="Albânia" />
			<Leaf zone_id="Europe/Berlin" name="Alemanha" />
			<Leaf zone_id="Europe/Andorra" name="Andorra" />
			<Leaf zone_id="Europe/Vienna" name="Áustria" />
			<Leaf zone_id="Europe/Minsk" name="Belarus" />
			<Leaf zone_id="Europe/Brussels" name="Bélgica" />
			<Leaf zone_id="Europe/Sarajevo" name="Bósnia &amp; Herzegovina" />
			<Leaf zone_id="Europe/Sofia" name="Bulgária" />
			<Leaf zone_id="Europe/Zagreb" name="Croácia" />
			<Leaf zone_id="Asia/Nicosia" name="Chipre" />
			<Leaf zone_id="Europe/Copenhagen" name="Dinamarca" />
			<Leaf zone_id="Europe/Bratislava" name="Eslováquia" />
			<Leaf zone_id="Europe/Ljubljana" name="Eslovênia" />
			<Leaf zone_id="Europe/Madrid" name="Espanha" />
			<Leaf zone_id="Europe/Tallinn" name="Estônia" />
			<Leaf zone_id="Europe/Helsinki" name="Finlândia" />
			<Leaf zone_id="Europe/Paris" name="França" />
			<Leaf zone_id="Europe/Gibraltar" name="Gibraltar" />
			<Leaf zone_id="Europe/Athens" name="Grécia" />
			<Leaf zone_id="Europe/Guernsey" name="Guernsey" />
			<Leaf zone_id="Europe/Amsterdam" name="Holanda" />
			<Leaf zone_id="Europe/Budapest" name="Hungria" />
			<Leaf zone_id="Europe/Isle_of_Man" name="Ilha de Man" />
			<Leaf zone_id="Europe/Mariehamn" name="Ilhas Åland" />
			<Leaf zone_id="Europe/Dublin" name="Ireland" />
			<Leaf zone_id="Atlantic/Reykjavik" name="Islândia" />
			<Leaf zone_id="Europe/Rome" name="Itália" />
			<Leaf zone_id="Europe/Jersey" name="Jersey" />
			<Leaf zone_id="Europe/Riga" name="Letônia" />
			<Leaf zone_id="Europe/Vaduz" name="Liechtenstein" />
			<Leaf zone_id="Europe/Vilnius" name="Lituânia" />
			<Leaf zone_id="Europe/Luxembourg" name="Luxemburgo" />
			<Leaf zone_id="Europe/Skopje" name="Macedônia" />
			<Leaf zone_id="Europe/Malta" name="Malta" />
			<Leaf zone_id="Europe/Chisinau" name="Moldávia" />
			<Leaf zone_id="Europe/Monaco" name="Mônaco" />
			<Leaf zone_id="Europe/Podgorica" name="Montenegro" />
			<Leaf zone_id="Europe/Oslo" name="Noruega" />
			<Leaf zone_id="Europe/Warsaw" name="Polônia" />
			<Leaf zone_id="Europe/Lisbon" name="Portugal" />
			<Leaf zone_id="Europe/Prague" name="República Tcheca" />
			<Leaf zone_id="Europe/Bucharest" name="Romênia" />
			<Branch name="Rússia">
				<Leaf zone_id="Europe/Volgograd" name="Moscou+00 - Caspian Sea" />
				<Leaf zone_id="Europe/Moscow" name="Moscou+00 - W Russia" />
				<Leaf zone_id="Europe/Samara" name="Moscou+01 - Samara, Udmurtia" />
				<Leaf zone_id="Europe/Kaliningrad" name="Moscou-01 - Kaliningrad" />
			</Branch>
			<Leaf zone_id="Europe/San_Marino" name="San Marino" />
			<Leaf zone_id="Europe/Belgrade" name="Sérvia" />
			<Leaf zone_id="Europe/Stockholm" name="Suécia" />
			<Leaf zone_id="Europe/Zurich" name="Suíça" />
			<Leaf zone_id="Europe/Istanbul" name="Turquia" />
			<Leaf zone_id="Europe/London" name="Reino Unido" />
			<Branch name="Ucrânia">
				<Leaf zone_id="Europe/Kiev" name="Ucrânia (maior parte)" />
				<Leaf zone_id="Europe/Simferopol" name="Central Crimea" />
				<Leaf zone_id="Europe/Uzhgorod" name="Ruthenia" />
				<Leaf zone_id="Europe/Zaporozhye" name="Zaporizhia, E Luhansk" />
			</Branch>
			<Leaf zone_id="Europe/Vatican" name="Vaticano" />
		</Branch>
		<Branch name="Cidades">
			<Leaf zone_id="Europe/Amsterdam" name="Amsterdã" />
			<Leaf zone_id="Europe/Andorra" name="Andorra la Vella" />
			<Leaf zone_id="Europe/Athens" name="Atena" />
			<Leaf zone_id="Europe/Madrid" name="Barcelona">
				<Coordinates latitude="41.388" longitude="2.17" />
			</Leaf>
			<Leaf zone_id="Europe/London" name="Belfast">
				<Coordinates latitude="54.597" longitude="-5.930" />
			</Leaf>
			<Leaf zone_id="Europe/Belgrade" name="Belgrado" />
			<Leaf zone_id="Europe/Berlin" name="Berlim" />
			<Leaf zone_id="Europe/Bratislava" name="Bratislava" />
			<Leaf zone_id="Europe/Brussels" name="Bruxelas" />
			<Leaf zone_id="Europe/Bucharest" name="Bucareste" />
			<Leaf zone_id="Europe/Budapest" name="Budapeste" />
			<Leaf zone_id="Europe/Chisinau" name="Chisinau" />
			<Leaf zone_id="Europe/Vatican" name="Cidade do Vaticano" />
			<Leaf zone_id="Europe/Copenhagen" name="Copenhagen" />
			<Leaf zone_id="Europe/Isle_of_Man" name="Douglas" />
			<Leaf zone_id="Europe/Dublin" name="Dublin" />
			<Leaf zone_id="Europe/Stockholm" name="Estocolmo" />
			<Leaf zone_id="Europe/Gibraltar" name="Gibraltar" />
			<Leaf zone_id="Europe/Helsinki" name="Helsinki" />
			<Leaf zone_id="Europe/Istanbul" name="Istanbul" />
			<Leaf zone_id="Europe/Kaliningrad" name="Kaliningrad" />
			<Leaf zone_id="Europe/Kiev" name="Kiev" />
			<Leaf zone_id="Europe/Lisbon" name="Lisboa" />
			<Leaf zone_id="Europe/Ljubljana" name="Ljubljana" />
			<Leaf zone_id="Europe/London" name="Londres" />
			<Leaf zone_id="Europe/Luxembourg" name="Cidade de Luxemburgo" />
			<Leaf zone_id="Europe/Madrid" name="Madri" />
			<Leaf zone_id="Europe/Malta" name="Malta" />
			<Leaf zone_id="Europe/Mariehamn" name="Mariehamn" />
			<Leaf zone_id="Europe/Minsk" name="Minsk" />
			<Leaf zone_id="Europe/Monaco" name="Monte Carlo" />
			<Leaf zone_id="Europe/Moscow" name="Moscou" />
			<Leaf zone_id="Asia/Nicosia" name="Nicosia" />
			<Leaf zone_id="Europe/Oslo" name="Oslo" />
			<Leaf zone_id="Europe/Paris" name="Paris" />
			<Leaf zone_id="Europe/Podgorica" name="Podgorica" />
			<Leaf zone_id="Europe/Prague" name="Praga" />
			<Leaf zone_id="Atlantic/Reykjavik" name="Reykjavik" />
			<Leaf zone_id="Europe/Riga" name="Riga" />
			<Leaf zone_id="Europe/Rome" name="Roma" />
			<Leaf zone_id="Europe/Jersey" name="St Helier" />
			<Leaf zone_id="Europe/Guernsey" name="St Peter Port" />
			<Leaf zone_id="Europe/Samara" name="Samara" />
			<Leaf zone_id="Europe/San_Marino" name="San Marino" />
			<Leaf zone_id="Europe/Sarajevo" name="Sarajevo" />
			<Leaf zone_id="Europe/Simferopol" name="Simferopol" />
			<Leaf zone_id="Europe/Skopje" name="Skopje" />
			<Leaf zone_id="Europe/Sofia" name="Sofia" />
			<Leaf zone_id="Europe/Tallinn" name="Tallinn" />
			<Leaf zone_id="Europe/Tirane" name="Tirana" />
			<Leaf zone_id="Europe/Uzhgorod" name="Uzhhorod" />
			<Leaf zone_id="Europe/Vaduz" name="Vaduz" />
			<Leaf zone_id="Europe/Vienna" name="Viena" />
			<Leaf zone_id="Europe/Vilnius" name="Vilnius" />
			<Leaf zone_id="Europe/Volgograd" name="Volgograd" />
			<Leaf zone_id="Europe/Warsaw" name="Warsaw" />
			<Leaf zone_id="Europe/Zagreb" name="Zagreb" />
			<Leaf zone_id="Europe/Zaporozhye" name="Zaporizhia" />
			<Leaf zone_id="Europe/Zurich" name="Zurich" />
		</Branch>
	</Branch>
	<Branch name="Oceano Índico">
		<Leaf zone_id="Indian/Chagos" name="Território Britânico do Oceano Índico" />
		<Leaf zone_id="Indian/Christmas" name="Ilha Christmas" />
		<Leaf zone_id="Indian/Cocos" name="Ilha do Coco" />
		<Leaf zone_id="Indian/Comoro" name="Ilhas Comoro" />
		<Leaf zone_id="Indian/Kerguelen" name="Terras Austrais e Antárticas Francesas" />
		<Leaf zone_id="Indian/Maldives" name="Maldivas" />
		<Leaf zone_id="Indian/Mauritius" name="Maurício" />
		<Leaf zone_id="Indian/Mayotte" name="Maiote" />
		<Leaf zone_id="Indian/Reunion" name="Reunião" />
		<Leaf zone_id="Indian/Mahe" name="Seicheles" />
	</Branch>
	<Branch name="Oceano Pacífico">
		<Branch name="Países">
			<Branch name="Chile">
				<Leaf zone_id="Pacific/Easter" name="Easter I &amp; Sala y Gómez" />
			</Branch>
			<Leaf zone_id="Pacific/Rarotonga" name="Cook Is" />
			<Branch name="Equador">
				<Leaf zone_id="Pacific/Galapagos" name="Galápagos Is" />
			</Branch>
			<Leaf zone_id="Pacific/Fiji" name="Fiji" />
			<Branch name="French Polynesia">
				<Leaf zone_id="Pacific/Gambier" name="Gambier Is" />
				<Leaf zone_id="Pacific/Marquesas" name="Marquesas Is" />
				<Leaf zone_id="Pacific/Tahiti" name="Society Is" />
			</Branch>
			<Leaf zone_id="Pacific/Guam" name="Guam" />
			<Branch name="Kiribati">
				<Leaf zone_id="Pacific/Tarawa" name="Gilbert Is" />
				<Leaf zone_id="Pacific/Kiritimati" name="Line Is" />
				<Leaf zone_id="Pacific/Enderbury" name="Phoenix Is" />
			</Branch>
			<Branch name="Marshall Islands">
				<Leaf zone_id="Pacific/Majuro" name="Marshall Is (most)" />
				<Leaf zone_id="Pacific/Kwajalein" name="Kwajalein" />
			</Branch>
			<Branch name="Micronésia">
				<Leaf zone_id="Pacific/Kosrae" name="Kosrae" />
				<Leaf zone_id="Pacific/Ponape" name="Ponape" />
				<Leaf zone_id="Pacific/Truk" name="Truk &amp; Yap" />
			</Branch>
			<Leaf zone_id="Pacific/Nauru" name="Nauru" />
			<Leaf zone_id="Pacific/Noumea" name="Nova Caledônia" />
			<Leaf zone_id="Pacific/Auckland" name="Nova Zelândia" />
			<Leaf zone_id="Pacific/Chatham" name="Nova Zelândia - Ilhas Chatham" />
			<Leaf zone_id="Pacific/Niue" name="Niue" />
			<Leaf zone_id="Pacific/Norfolk" name="Norfolk I" />
			<Leaf zone_id="Pacific/Saipan" name="N Mariana Is" />
			<Leaf zone_id="Pacific/Palau" name="Palau" />
			<Leaf zone_id="Pacific/Port_Moresby" name="Papua Nova Guiné" />
			<Leaf zone_id="Pacific/Pitcairn" name="Pitcairn I" />
			<Leaf zone_id="Pacific/Pago_Pago" name="Samoa, Americana" />
			<Leaf zone_id="Pacific/Apia" name="Samoa, Ocidental" />
			<Leaf zone_id="Pacific/Guadalcanal" name="Ilhas Salomão" />
			<Leaf zone_id="Pacific/Fakaofo" name="Tokelau" />
			<Leaf zone_id="Pacific/Tongatapu" name="Tonga" />
			<Leaf zone_id="Pacific/Funafuti" name="Tuvalu" />
			<Branch name="US Minor Outlying Is">
				<Leaf zone_id="Pacific/Johnston" name="Johnston Atoll" />
				<Leaf zone_id="Pacific/Midway" name="Midway Is" />
				<Leaf zone_id="Pacific/Wake" name="Wake I" />
			</Branch>
			<Leaf zone_id="Pacific/Efate" name="Vanuatu" />
			<Leaf zone_id="Pacific/Wallis" name="Wallis &amp; Futuna" />
		</Branch>
		<Branch name="Cidades">
			<Leaf zone_id="Pacific/Niue" name="Alofi" />
			<Leaf zone_id="Pacific/Apia" name="Apia" />
			<Leaf zone_id="Pacific/Auckland" name="Auckland" />
			<Leaf zone_id="Pacific/Rarotonga" name="Avarua" />
			<Leaf zone_id="Pacific/Funafuti" name="Funafuti" />
			<Leaf zone_id="Pacific/Guadalcanal" name="Honiara" />
			<Leaf zone_id="Pacific/Kiritimati" name="Kiritimati" />
			<Leaf zone_id="Pacific/Majuro" name="Majuro" />
			<Leaf zone_id="Pacific/Palau" name="Melekeok" />
			<Leaf zone_id="Pacific/Noumea" name="Nouméa" />
			<Leaf zone_id="Pacific/Tongatapu" name="Nuku'alofa" />
			<Leaf zone_id="Pacific/Pago_Pago" name="Pago Pago" />
			<Leaf zone_id="Pacific/Tahiti" name="Papeete" />
			<Leaf zone_id="Pacific/Port_Moresby" name="Port Moresby" />
			<Leaf zone_id="Pacific/Efate" name="Port Vila" />
			<Leaf zone_id="Pacific/Saipan" name="Saipan" />
			<Leaf zone_id="Pacific/Tarawa" name="South Tarawa" />
			<Leaf zone_id="Pacific/Fiji" name="Suva" />
			<Leaf zone_id="Pacific/Auckland" name="Wellington">
				<Coordinates latitude="-41.286" longitude="174.776" />
			</Leaf>
			<Leaf zone_id="Pacific/Nauru" name="Yaren" />
		</Branch>
	</Branch>
	<Leaf zone_id="Etc/UTC" name="GMT/UTC" />
</zonepicker>
<!-- Do not remove this comment
*
*
*
*
*
*
*
*
*
*
*
*
*
*
*
*
*
*
*
*
*
*
*
*
*
*
*
*
*
*
*
*
*
-->